huaweicloudsdkrms/__init__.py
huaweicloudsdkrms/v1/__init__.py
huaweicloudsdkrms/v1/rms_async_client.py
huaweicloudsdkrms/v1/rms_client.py
huaweicloudsdkrms/v1/model/__init__.py
huaweicloudsdkrms/v1/model/account_aggregation_source.py
huaweicloudsdkrms/v1/model/aggregate_compliance_detail_request.py
huaweicloudsdkrms/v1/model/aggregate_discovered_resource_counts_request.py
huaweicloudsdkrms/v1/model/aggregate_discovered_resources_request.py
huaweicloudsdkrms/v1/model/aggregate_policy_assignment_detail_request.py
huaweicloudsdkrms/v1/model/aggregate_policy_assignments.py
huaweicloudsdkrms/v1/model/aggregate_policy_assignments_filters.py
huaweicloudsdkrms/v1/model/aggregate_policy_assignments_request.py
huaweicloudsdkrms/v1/model/aggregate_policy_compliance_summary_result.py
huaweicloudsdkrms/v1/model/aggregate_policy_states_request.py
huaweicloudsdkrms/v1/model/aggregate_resource_config_request.py
huaweicloudsdkrms/v1/model/aggregated_source_status.py
huaweicloudsdkrms/v1/model/aggregation_authorization_request.py
huaweicloudsdkrms/v1/model/aggregation_authorization_resp.py
huaweicloudsdkrms/v1/model/channel_config_body.py
huaweicloudsdkrms/v1/model/collect_all_resources_summary_request.py
huaweicloudsdkrms/v1/model/collect_all_resources_summary_response.py
huaweicloudsdkrms/v1/model/compliance.py
huaweicloudsdkrms/v1/model/configuration_aggregator_request.py
huaweicloudsdkrms/v1/model/configuration_aggregator_resp.py
huaweicloudsdkrms/v1/model/count_all_resources_request.py
huaweicloudsdkrms/v1/model/count_all_resources_response.py
huaweicloudsdkrms/v1/model/create_aggregation_authorization_request.py
huaweicloudsdkrms/v1/model/create_aggregation_authorization_response.py
huaweicloudsdkrms/v1/model/create_configuration_aggregator_request.py
huaweicloudsdkrms/v1/model/create_configuration_aggregator_response.py
huaweicloudsdkrms/v1/model/create_organization_policy_assignment_request.py
huaweicloudsdkrms/v1/model/create_organization_policy_assignment_response.py
huaweicloudsdkrms-3.1.184.dist-info/METADATA
huaweicloudsdkrms-3.1.184.dist-info/WHEEL
huaweicloudsdkrms-3.1.184.dist-info/licenses/LICENSE
huaweicloudsdkrms-3.1.184.dist-info/RECORD
